enalog_cli/__init__.py
enalog_cli/main.py
enalog_cli-0.1.1.dist-info/METADATA
enalog_cli-0.1.1.dist-info/entry_points.txt
enalog_cli-0.1.1.dist-info/WHEEL
enalog_cli-0.1.1.dist-info/RECORD
