Metadata-Version: 2.1
Name: enalog-cli
Version: 0.1.1
Summary: EnaLog CLI
Author: Sam Newby
Author-email: sam@enalog.app
Requires-Python: >=3.9,<4.0
Classifier: Programming Language :: Python :: 3
Classifier: Programming Language :: Python :: 3.9
Classifier: Programming Language :: Python :: 3.10
Classifier: Programming Language :: Python :: 3.11
Requires-Dist: requests (>=2.29.0,<3.0.0)
Requires-Dist: typer[all] (>=0.7.0,<0.8.0)
